subpaths/__init__.py
subpaths/subpaths.py
subpaths/tests/__init__.py
subpaths/tests/test_subpaths.py
subpaths-0.2.0.dist-info/LICENSE
subpaths-0.2.0.dist-info/METADATA
subpaths-0.2.0.dist-info/WHEEL
subpaths-0.2.0.dist-info/top_level.txt
subpaths-0.2.0.dist-info/RECORD
