Metadata-Version: 2.1
Name: subpaths
Version: 0.2.0
Summary: Finding common subpaths between paths.
Home-page: https://github.com/lawrencemq/subpaths
Author: Lawrence Weikum
Author-email: lweikum@gmail.com
License: MIT
Platform: UNKNOWN
Classifier: Programming Language :: Python :: 2.7
Classifier: Programming Language :: Python :: 3
Classifier: License :: OSI Approved :: MIT License
Classifier: Development Status :: 4 - Beta
Classifier: Operating System :: OS Independent
Classifier: Natural Language :: English
Classifier: Topic :: Software Development :: Libraries
Classifier: Topic :: Utilities
